mercadopago_dx-0.0.1.dev0.dist-info/DESCRIPTION.rst
mercadopago_dx-0.0.1.dev0.dist-info/LICENSE.txt
mercadopago_dx-0.0.1.dev0.dist-info/METADATA
mercadopago_dx-0.0.1.dev0.dist-info/RECORD
mercadopago_dx-0.0.1.dev0.dist-info/WHEEL
mercadopago_dx-0.0.1.dev0.dist-info/metadata.json
mercadopago_dx-0.0.1.dev0.dist-info/top_level.txt
sdk/__init__.py
sdk/sdk.py
sdk/core/__init__.py
sdk/core/credential.py
sdk/error/__init__.py
sdk/internal/__init__.py
sdk/internal/validator.py
sdk/net/__init__.py
sdk/net/credential_repository.py
sdk/net/net_client.py
