Metadata-Version: 2.0
Name: mercadopago-dx
Version: 0.0.1.dev0
Summary: Devtools for MercadoPago services
Home-page: https://github.com/mercadopago/dx-python
Author: Lucas Emmanuel Bais
Author-email: developers@mercadolibre.com
License: MIT
Keywords: mercadopago sdk development
Platform: any
Classifier: Environment :: Web Environment
Classifier: Intended Audience :: Developers
Classifier: Operating System :: OS Independent
Classifier: Programming Language :: Python :: 2
Classifier: Programming Language :: Python :: 2.6
Classifier: Programming Language :: Python :: 2.7
Classifier: Topic :: Software Development :: Libraries :: Application Frameworks
Classifier: Topic :: Software Development :: Libraries :: Python Modules
Requires-Dist: certifi (>=2018.1.18)
Requires-Dist: chardet (>=3.0.4)
Requires-Dist: idna (>=2.6)
Requires-Dist: requests (>=2.18.4)
Requires-Dist: urllib3 (>=1.22)
